metagadget/__init__.py
metagadget-0.0.4.dist-info/LICENSE
metagadget-0.0.4.dist-info/METADATA
metagadget-0.0.4.dist-info/WHEEL
metagadget-0.0.4.dist-info/top_level.txt
metagadget-0.0.4.dist-info/RECORD
