Metadata-Version: 2.1
Name: metagadget
Version: 0.0.4
Summary: IoT Framework for Event-Triggered Integration of User-Developed Devices into Commercial Metaverse Platforms
Author-email: Ryutaro Kurai <ryu.kurai@gmail.com>, Takefumi Hiraki <t.hiraki@cluster.mu>
Project-URL: Homepage, https://github.com/cluster-lab/MetaGadget
Project-URL: Issues, https://github.com/cluster-lab/MetaGadget/issues
Classifier: Programming Language :: Python :: 3
Classifier: License :: OSI Approved :: Apache Software License
Classifier: Operating System :: OS Independent
Requires-Python: >=3.8
License-File: LICENSE
Requires-Dist: Werkzeug ~=3.0.4
Requires-Dist: ngrok ~=1.4.0
